README.md
setup.py
euler_logger_service.egg-info/PKG-INFO
euler_logger_service.egg-info/SOURCES.txt
euler_logger_service.egg-info/dependency_links.txt
euler_logger_service.egg-info/entry_points.txt
euler_logger_service.egg-info/top_level.txt
logger/__init__.py
logger/constants.py
logger/log_handler.py