Metadata-Version: 1.0
Name: euler-logger-service
Version: 0.2
Summary: This is a logger service module.
Home-page: https://github.com/atulyaduvanshieuler/logger_service
Author: Poorvak Kapoor
Author-email: poorvak.kapoor@eulermotors.com
License: UNKNOWN
Platform: UNKNOWN
